LICENSE
MANIFEST.in
README.md
setup.py
django_qunit/__init__.py
django_qunit/snippet_loader.py
django_qunit/urls.py
django_qunit/views.py
django_qunit2.egg-info/PKG-INFO
django_qunit2.egg-info/SOURCES.txt
django_qunit2.egg-info/dependency_links.txt
django_qunit2.egg-info/top_level.txt
django_qunit/static/css/qunit.css
django_qunit/static/js/qunit.js
django_qunit/templates/__init__.py
django_qunit/templates/qunit/index.html