Metadata-Version: 1.0
Name: django-qunit2
Version: 20130822
Summary: QUnit Javascript testing integration for Django.
Home-page: http://github.com/turtlemonvh/django-qunit/
Author: Timothy Van Heest
Author-email: timothy.vanheest@gmail.com
License: UNKNOWN
Platform: UNKNOWN
Classifier: Development Status :: 3 - Alpha
Classifier: Environment :: Web Environment
Classifier: Framework :: Django
Classifier: Intended Audience :: Developers
Classifier: License :: OSI Approved :: MIT License
Classifier: Operating System :: OS Independent
Classifier: Programming Language :: Python
Classifier: Programming Language :: Python :: 2.6
Classifier: Programming Language :: Python :: 2.7
Classifier: Programming Language :: JavaScript
Classifier: Topic :: Software Development :: Testing
